aiosiduck-0.1.2.dist-info/METADATA
aiosiduck-0.1.2.dist-info/WHEEL
aiosiduck/__init__.py
aiosiduck/quic_client_protocol.py
aiosiduck-0.1.2.dist-info/RECORD
