Metadata-Version: 2.1
Name: aiosiduck
Version: 0.1.2
Summary: simple siduck for quic
Author-Email: sothis <382035562@qq.com>
License: MIT
Requires-Python: >=3.8
Requires-Dist: aioquic>=0.9.25
